ImproveMP/__init__.py
ImproveMP/main.py
ImproveMP-0.1.0.dist-info/LICENSE
ImproveMP-0.1.0.dist-info/METADATA
ImproveMP-0.1.0.dist-info/WHEEL
ImproveMP-0.1.0.dist-info/top_level.txt
ImproveMP-0.1.0.dist-info/RECORD
