Metadata-Version: 2.1
Name: ImproveMP
Version: 0.1.0
Summary: Uma biblioteca feita para criar inputs automáticos para o Quantum Espresso, com dados do Materials Project
Home-page: https://github.com/cauaschuch/ImproveMP
Author: Cauã Ferrazza Schuch, Eduardo Gadelha, Pedro Bueno e Luisa Belentani
Author-email: caua.ferrazza@gmail.com
License: MIT
Platform: UNKNOWN
Classifier: Programming Language :: Python :: 3
Classifier: License :: OSI Approved :: MIT License
Classifier: Operating System :: OS Independent
Requires-Python: >=3.6
License-File: LICENSE
Requires-Dist: mp-api
Requires-Dist: numpy
